dataset_vo/__init__.py
dataset_vo/dataset_vo.py
nktest/__init__.py
nktest/nktest.py
torch-nk_5/__init__.py
torch-nk_5/dataset_vo.py
torch-nk_5/torch_nk_5.py
torch_nk/__init__.py
torch_nk/torch_nk.py
torch_nk_6/__init__.py
torch_nk_6/torch_nk_6.py
torch_nkill/__init__.py
torch_nkill/dataset_vo.py
torch_nkill/torch_nkill.py
torch_nk_6-0.1.dist-info/METADATA
torch_nk_6-0.1.dist-info/WHEEL
torch_nk_6-0.1.dist-info/top_level.txt
torch_nk_6-0.1.dist-info/RECORD
