Metadata-Version: 2.1
Name: torch-nk-6
Version: 0.1
Summary: your mind
Home-page: https://github.com/nobug-code/test_nk_2
Author: Namgil Kim
Author-email: tompx7564@gmail.com
License: UNKNOWN
Keywords: torch
Platform: UNKNOWN
Classifier: Programming Language :: Python :: 3
Classifier: Programming Language :: Python :: 3.6
Classifier: Programming Language :: Python :: 3.7
Requires-Python: >=3.6
Requires-Dist: torch
Requires-Dist: torchvision
Requires-Dist: h5py
Requires-Dist: tqdm
Requires-Dist: opencv-python
Requires-Dist: requests
Requires-Dist: numpy
